ctap_keyring_device/__init__.py
ctap_keyring_device/ctap_credential_maker.py
ctap_keyring_device/ctap_keyring_device.py
ctap_keyring_device/ctap_private_key_wrapper.py
ctap_keyring_device/ctap_strucs.py
ctap_keyring_device/user_verifiers/__init__.py
ctap_keyring_device/user_verifiers/ctap_user_verifier.py
ctap_keyring_device/user_verifiers/ctap_user_verifier_factory.py
ctap_keyring_device/user_verifiers/noop_ctap_user_verifier.py
ctap_keyring_device/user_verifiers/touch_id_ctap_user_verifier.py
ctap_keyring_device/user_verifiers/windows_hello_ctap_user_verifier.py
ctap_keyring_device-1.0.6.dist-info/LICENSE
ctap_keyring_device-1.0.6.dist-info/METADATA
ctap_keyring_device-1.0.6.dist-info/WHEEL
ctap_keyring_device-1.0.6.dist-info/top_level.txt
ctap_keyring_device-1.0.6.dist-info/RECORD
