Metadata-Version: 2.1
Name: ctap-keyring-device
Version: 1.0.6
Summary: CTAP (client-to-authenticator-protocol) device backed by python's keyring library
Home-page: https://github.com/dany74q/ctap-keyring-device
Author: Danny Shemesh
Author-email: dany74q@gmail.com
License: UNKNOWN
Platform: UNKNOWN
Classifier: Development Status :: 5 - Production/Stable
Classifier: Intended Audience :: Developers
Classifier: License :: OSI Approved :: MIT License
Classifier: Programming Language :: Python :: 3
Requires-Python: >=3.6
Provides-Extra: testing
Provides-Extra: docs
